mkdocs_obsidian/__init__.py
mkdocs_obsidian/__main__.py
mkdocs_obsidian/test_sample.py
mkdocs_obsidian/common/__init__.py
mkdocs_obsidian/common/admonition.py
mkdocs_obsidian/common/config.py
mkdocs_obsidian/common/conversion.py
mkdocs_obsidian/common/convert_all.py
mkdocs_obsidian/common/convert_one.py
mkdocs_obsidian/common/file_checking.py
mkdocs_obsidian/common/github_push.py
mkdocs_obsidian/common/global_value.py
mkdocs_obsidian/common/metadata.py
obs2mk-5.0.0.dist-info/LICENSE
obs2mk-5.0.0.dist-info/METADATA
obs2mk-5.0.0.dist-info/WHEEL
obs2mk-5.0.0.dist-info/entry_points.txt
obs2mk-5.0.0.dist-info/top_level.txt
obs2mk-5.0.0.dist-info/RECORD
