Metadata-Version: 2.1
Name: obs2mk
Version: 5.0.0
Summary: A script to share your obsidian vault (in partial way) using mkdocs
Home-page: https://github.com/Mara-Li/mkdocs_obsidian_publish
Author: Mara-Li
Author-email: mara-li@icloud.com
License: AGPL
Keywords: obsidian,obsidian.md,free publish,publish,mkdocs,material
Classifier: Natural Language :: English
Classifier: Natural Language :: French
Classifier: Topic :: Text Processing :: Markup :: Markdown
Classifier: License :: OSI Approved :: GNU Affero General Public License v3 or later (AGPLv3+)
Classifier: Programming Language :: Python :: 3.9
Requires-Python: >=3.10
License-File: LICENSE
Requires-Dist: click (>=8.1.3)
Requires-Dist: clipboard (>=0.0.4)
Requires-Dist: colorama (>=0.4.4)
Requires-Dist: commonmark (>=0.9.1)
Requires-Dist: gitdb (>=4.0.9)
Requires-Dist: gitpython (>=3.1.27)
Requires-Dist: mypy-extensions (>=0.4.3)
Requires-Dist: pathspec (>=0.9.0)
Requires-Dist: platformdirs (>=2.5.2)
Requires-Dist: pygments (>=2.12.0)
Requires-Dist: pyperclip (>=1.8.2)
Requires-Dist: python-dotenv (>=0.20.0)
Requires-Dist: python-frontmatter (>=1.0.0)
Requires-Dist: pyyaml (>=6.0)
Requires-Dist: rich (>=12.4.4)
Requires-Dist: setuptools (>=62.3.2)
Requires-Dist: smmap (>=5.0.0)
Requires-Dist: unidecode (>=1.3.4)
Requires-Dist: toml (>=0.10.2)
Requires-Dist: wemake-python-styleguide
Requires-Dist: pyformat
Requires-Dist: pre-commit
